odoo/addons/calendar_ical_enhancements/__init__.py
odoo/addons/calendar_ical_enhancements/__manifest__.py
odoo/addons/calendar_ical_enhancements/models/__init__.py
odoo/addons/calendar_ical_enhancements/models/calendar.py
odoo12_addon_calendar_ical_enhancements-12.0.1.0.0.dist-info/METADATA
odoo12_addon_calendar_ical_enhancements-12.0.1.0.0.dist-info/WHEEL
odoo12_addon_calendar_ical_enhancements-12.0.1.0.0.dist-info/top_level.txt
odoo12_addon_calendar_ical_enhancements-12.0.1.0.0.dist-info/RECORD
